{
    "mode": "light",
    "content": "dark-content",
    "primaryColor": "#2E89DB",
    "primaryLightColor": "#89c2f5",
    "secondaryColor": "#FFCFDB",
    "secondaryLightColor": "#FFCFDB",
    "defaultColor": "#141446",
    "background": "#111520",
    "backgroundLight": "#f9f9f9",
    "secondaryBG": "#f8f8f8",
    "text": "#FFF",
    "textLight": "#999",
    "textBold": "#FFF",
    "iconBG": "#2E89DB",
    "iconColor": "#99989E",
    "borderColor": "#ddd",
    "btnTextColor": "#fff",
    "btnBGColor": "#2E89DB",
    "disableBtnBGColor": "#C9CAD4",
    "bottomTabBGColor": "#FFF",
    "headerBGColor": "#111520",
    "headerTextColor": "#FFF",
    "inputBG": "#1C1C1E",
    "errorColor": "#F26A6A",
    "activeTabBG": "#FFF"
}